eksitui/__init__.py
eksitui/__main__.py
eksitui/content.py
eksitui/gen_token.py
eksitui/loading.py
eksitui/main.css
eksitui/main.py
eksitui/query_id.py
eksitui/topic_list.py
eksitui/utils.py
eksitui-0.1.4.dist-info/entry_points.txt
eksitui-0.1.4.dist-info/METADATA
eksitui-0.1.4.dist-info/WHEEL
eksitui-0.1.4.dist-info/RECORD
