Metadata-Version: 2.1
Name: eksitui
Version: 0.1.4
Summary: TUI for Turkish collaborative hypertext dictionary ekşi sözlük.
Home-page: https://github.com/agmmnn/eksitui
Keywords: eksi,turkish,sozluk,cli,eksisozluk,tui
Author: Gökçe
Author-email: agmmnn@gmail.com
Requires-Python: >=3.7,<4.0
Classifier: Environment :: Console
Classifier: Operating System :: OS Independent
Classifier: Programming Language :: Python :: 3
Classifier: Programming Language :: Python :: 3.7
Classifier: Programming Language :: Python :: 3.8
Classifier: Programming Language :: Python :: 3.9
Classifier: Programming Language :: Python :: 3.10
Classifier: Programming Language :: Python :: 3.11
Classifier: Programming Language :: Python :: 3
Classifier: Topic :: Utilities
Requires-Dist: requests (>=2.28.1,<3.0.0)
Requires-Dist: textual (>=0.8.0,<0.9.0)
Project-URL: Bug Tracker, https://github.com/agmmnn/eksitui/issues
Project-URL: Changelog, https://github.com/agmmnn/eksitui/releases
Project-URL: Repository, https://github.com/agmmnn/eksitui
Project-URL: Source, https://github.com/agmmnn/eksitui
